jobview/__init__.py
jobview/main.py
jobview/record_resource.py
jobview/show_nodes.py
jobview/show_status.py
jobview/src/SimHei.ttf
jobview/version/version.json
jobview-1.2.5.dist-info/METADATA
jobview-1.2.5.dist-info/WHEEL
jobview-1.2.5.dist-info/entry_points.txt
jobview-1.2.5.dist-info/top_level.txt
jobview-1.2.5.dist-info/RECORD
