Metadata-Version: 2.2
Name: jobview
Version: 1.2.5
Summary: Tools for better recording and visualizing computer resources of Sun Grid Engine(SGE) System
Home-page: https://github.com/Bio-MingChen/jobview
Author: chenming
Author-email: cm.bio@qq.com
License: BSD License
Project-URL: Tracker, https://github.com/Bio-MingChen/jobview/issues
Classifier: Development Status :: 5 - Production/Stable
Classifier: Operating System :: OS Independent
Classifier: Intended Audience :: Developers
Classifier: License :: OSI Approved :: MIT License
Classifier: Programming Language :: Python
Classifier: Programming Language :: Python :: 3
Classifier: Programming Language :: Python :: 3.6
Classifier: Topic :: Software Development :: Libraries
Requires-Dist: click
Requires-Dist: matplotlib
Requires-Dist: plotly
Requires-Dist: humanfriendly
Dynamic: author
Dynamic: author-email
Dynamic: classifier
Dynamic: description
Dynamic: description-content-type
Dynamic: home-page
Dynamic: license
Dynamic: project-url
Dynamic: requires-dist
Dynamic: summary
